pairlink/__init__.py
pairlink/cointegration.py
pairlink/core.py
pairlink/distribution.py
pairlink/mean_reversion.py
pairlink/processing.py
pairlink-0.0.3.dist-info/licenses/LICENCE
pairlink-0.0.3.dist-info/METADATA
pairlink-0.0.3.dist-info/WHEEL
pairlink-0.0.3.dist-info/top_level.txt
pairlink-0.0.3.dist-info/RECORD
