Metadata-Version: 2.4
Name: pairlink
Version: 0.0.3
Summary: A package for statistical analysis and testing of relationships between 2 time series.
Home-page: https://www.developexx.com
Author: Anthony Gocmen
Author-email: anthony.gocmen@gmail.com
License: MIT
Requires-Python: >=3.11
License-File: LICENCE
Requires-Dist: pandas
Requires-Dist: numpy
Requires-Dist: statsmodels
Requires-Dist: scipy
Dynamic: author
Dynamic: author-email
Dynamic: description
Dynamic: description-content-type
Dynamic: home-page
Dynamic: license
Dynamic: license-file
Dynamic: requires-dist
Dynamic: requires-python
Dynamic: summary
